[{"id":1,"supplier_name":"PT. JAYA MULIA  BANGKIT SUKSES","supplier_address":"PARE-KEDIRI"},
{"id":2,"supplier_name":"PT. OETOMO AGRINDO ABADI","supplier_address":"SURABAYA"},
{"id":3,"supplier_name":"CV. SINAR AGUNG","supplier_address":"JOMBANG"},
{"id":4,"supplier_name":"PT. ZEKA AGRO PERKASA","supplier_address":"SURABAYA"},
{"id":5,"supplier_name":"PT. KEDIRI INDAH","supplier_address":"JOMBANG"},
{"id":6,"supplier_name":"SENTRA USAHA JAYA","supplier_address":"JAKARTA"},
{"id":7,"supplier_name":"CV. EKA NUSA JAYA","supplier_address":"MEDAN"},
{"id":8,"supplier_name":"PT. SURYA BUMI SENTOSA","supplier_address":"BANDAR LAMPUNG"},
{"id":9,"supplier_name":"CV. GENESIS","supplier_address":"BANDUNG"},
{"id":10,"supplier_name":"PT. SULOTCO JAYA ABADI","supplier_address":"BANDAR LAMPUNG"},
{"id":11,"supplier_name":"PT. DEMPO MANDIRI","supplier_address":"BANDAR LAMPUNG"},
{"id":12,"supplier_name":"CV. AGRI ANUGERAH LESTARI","supplier_address":"PARE"},
{"id":14,"supplier_name":"PT. SULOTCO JAYA ABADI.","supplier_address":"MAKASAR"},
{"id":16,"supplier_name":"TCE COFFEE TRADING LTD","supplier_address":"BRAZIL"},
{"id":17,"supplier_name":"PT. BINTANG TUNGGAL SEJATI","supplier_address":"SIDOARJO"},
{"id":18,"supplier_name":"PT. BINTANG TUNGGAL SEJATI","supplier_address":"SEPANJANG"},
{"id":19,"supplier_name":"CV. PAMENANG JAYA","supplier_address":"KEDIRI"},
{"id":20,"supplier_name":"PT. JAYA MULIA  BANGKIT SUKSES","supplier_address":"PARE"},
{"id":21,"supplier_name":"PT. SULOTCO JAYA ABADI","supplier_address":"TORAJA"},
{"id":22,"supplier_name":"PT. SULOTCO JAYA ABADI.","supplier_address":"TORAJA"},
{"id":23,"supplier_name":"PT. KEDIRI INDAH - JOMBANG","supplier_address":"JOMBANG"},
{"id":24,"supplier_name":"PT. SULOTCO JAYA ABADI'","supplier_address":"TEMANGGUNG"},
{"id":25,"supplier_name":"PT. ZEKA AGRO PERKASA","supplier_address":"GRESIK"},
{"id":26,"supplier_name":"CV. PANCA ADI JAYA","supplier_address":"SURABAYA"},
{"id":27,"supplier_name":"PT. SULOTCO JAYA ABADI\"","supplier_address":"JEMBER"},
{"id":28,"supplier_name":"PT. SUNDI MAJU SEJAHTERA","supplier_address":"BANDAR LAMPUNG"},
{"id":29,"supplier_name":"PT. ASIA MAKMUR","supplier_address":"BANDAR LAMPUNG"},
{"id":30,"supplier_name":"TRUCK","supplier_address":"BANDAR LAMPUNG"},
{"id":31,"supplier_name":"PT. SUMATRA MAKMUR SEJATI","supplier_address":"BANDAR LAMPUNG"}]